{
  "version": 2,
  "extractor": "pdffigures2",
  "figures": [
    {
      "url": "assets/figures/arxiv/2603.20583v2/fig-001.webp",
      "caption": "Fig. 4. Examples of ground-truth masks generated via our pipeline, illustrating the ego vehicle: (Top Left) executing a sharp right turn, (Top Right) initiating a parallel parking maneuver, (Bottom Left) cruising along a straight highway, and (Bottom Right) performing a lane change.",
      "page": 4,
      "index": 1,
      "width": 512,
      "height": 292
    },
    {
      "url": "assets/figures/arxiv/2603.20583v2/fig-002.webp",
      "caption": "Fig. 5. Pre-trained model predicted outputs shown in red and ground truth annotations in green.",
      "page": 6,
      "index": 2,
      "width": 1054,
      "height": 357
    },
    {
      "url": "assets/figures/arxiv/2603.20583v2/fig-003.webp",
      "caption": "Fig. 6. Scooter predictions: Finetuned (FT) and Trained from Scratch (TS)",
      "page": 6,
      "index": 3,
      "width": 512,
      "height": 255
    },
    {
      "url": "assets/figures/arxiv/2603.20583v2/fig-004.webp",
      "caption": "Fig. 1. Overview of the GHOST self-supervised trajectory estimation pipeline. The framework consists of three main stages: (1) SfM Pipeline: Raw uncalibrated video sequences are processed using COLMAP to extract sparse 3D point clouds and unscaled 6-DoF camera poses. (2) Post-Processing & Mask Generation: Ground points are recovered from the sequence’s sparse reconstruction; camera height is calculated; recovered height is used to project the trajectory onto the ground plane, generating spatially accurate Ground Truth (GT) masks. (3) Model Training: A segmentation model takes a batch of raw RGB images as input and predicts probabilistic spatial masks. The model is trained by calculating a weighted asymmetric loss L 2 between the predicted hypotheses and the auto-generated GT masks.",
      "page": 2,
      "index": 4,
      "width": 727,
      "height": 375
    }
  ]
}